yao_framework/__init__.py
yao_framework/install.jl
yao_framework/wrappers.py
yao_framework/yao.py
yao_framework-0.6.0.dist-info/LICENSE.md
yao_framework-0.6.0.dist-info/METADATA
yao_framework-0.6.0.dist-info/WHEEL
yao_framework-0.6.0.dist-info/top_level.txt
yao_framework-0.6.0.dist-info/RECORD
