Metadata-Version: 2.1
Name: yao-framework
Version: 0.6.0
Summary: Extensible Efficient Quantum Algorithm Design in Python
Home-page: https://github.com/QuantumBFS/Yao.jl
Author: Xiuzhe (Roger) Luo and Jinguo Liu
Author-email: roger.luo@uwaterloo.ca
License: Apache License 2.0
Keywords: differential equations stochastic ordinary delay differential-algebraic dae ode sde dde
Platform: UNKNOWN
Classifier: Development Status :: 4 - Beta
Classifier: Intended Audience :: Developers
Classifier: Intended Audience :: Education
Classifier: Intended Audience :: Science/Research
Classifier: License :: OSI Approved :: Apache Software License
Classifier: Programming Language :: Python :: 3.6
Classifier: Topic :: Scientific/Engineering
Classifier: Topic :: Scientific/Engineering :: Artificial Intelligence
Classifier: Topic :: Scientific/Engineering :: Physics
Requires-Dist: julia (>=0.2)
